zen_he/__init__.py
zen_he/en.py
zen_he/he.py
zen_of_python_he-0.0.1.dist-info/LICENSE
zen_of_python_he-0.0.1.dist-info/METADATA
zen_of_python_he-0.0.1.dist-info/WHEEL
zen_of_python_he-0.0.1.dist-info/top_level.txt
zen_of_python_he-0.0.1.dist-info/RECORD
