Metadata-Version: 2.1
Name: zen-of-python-he
Version: 0.0.1
Summary: Ultimite guide to life, python and all.
Home-page: https://github.com/tvruikuzui/zen_he
Author: Aharon Luzon
Author-email: ahron901@gmail.com
License: MIT
Platform: UNKNOWN
